nbprogress
