Metadata-Version: 2.1
Name: nbprogress
Version: 0.1.4
Summary: A lightweigth progressbar for jupyter notebook
Home-page: https://github.com/saberd/nbprogress
Author: saberd
Author-email: mail@saberd.com
License: UNKNOWN
Platform: UNKNOWN
Classifier: Topic :: Scientific/Engineering :: Artificial Intelligence
Classifier: Programming Language :: Python :: 3.6
Classifier: Programming Language :: Python :: 3.7
Classifier: License :: OSI Approved :: MIT License
Classifier: Topic :: Utilities
Requires-Python: >=3.*
